mathy_core/__init__.py
mathy_core/about.py
mathy_core/expressions.meta.json
mathy_core/expressions.py
mathy_core/layout.py
mathy_core/parser.py
mathy_core/problems.py
mathy_core/py.typed
mathy_core/rule.py
mathy_core/testing.py
mathy_core/tokenizer.py
mathy_core/tree.py
mathy_core/types.py
mathy_core/util.py
mathy_core/rules/__init__.py
mathy_core/rules/associative_swap.py
mathy_core/rules/associative_swap.test.json
mathy_core/rules/balanced_move.py
mathy_core/rules/balanced_move.test.json
mathy_core/rules/commutative_swap.py
mathy_core/rules/commutative_swap.test.json
mathy_core/rules/constants_simplify.py
mathy_core/rules/constants_simplify.test.json
mathy_core/rules/distributive_factor_out.py
mathy_core/rules/distributive_factor_out.test.json
mathy_core/rules/distributive_multiply_across.py
mathy_core/rules/distributive_multiply_across.test.json
mathy_core/rules/multiplicative_inverse.py
mathy_core/rules/multiplicative_inverse.test.json
mathy_core/rules/restate_subtraction.py
mathy_core/rules/restate_subtraction.test.json
mathy_core/rules/variable_multiply.py
mathy_core/rules/variable_multiply.test.json
tests/__init__.py
tests/conftest.py
tests/search_tree.py
tests/test_expressions.py
tests/test_layout.py
tests/test_parser.py
tests/test_problems.py
tests/test_rules.py
tests/test_tokenizer.py
tests/test_tree.py
tests/test_tree_node.py
tests/test_util.py
website/__init__.py
website/tests/__init__.py
website/tests/cas/__init__.py
website/tests/cas/test_overview.py
website/tests/cas/test_tokenizer_manual.py
website/tests/cas/test_tokenizer_tokenize.py
website/tests/rules/__init__.py
website/tests/rules/test_rules_overview.py
website/tools/__init__.py
website/tools/docs.py
mathy_core-0.9.5.dist-info/LICENSE.md
mathy_core-0.9.5.dist-info/METADATA
mathy_core-0.9.5.dist-info/WHEEL
mathy_core-0.9.5.dist-info/top_level.txt
mathy_core-0.9.5.dist-info/RECORD
