Metadata-Version: 2.2
Name: mathy_core
Version: 0.9.5
Summary: Computer Algebra System for working with math expressions
Home-page: https://mathy.ai
Author: Justin DuJardin
Author-email: justin@dujardinconsulting.com
License: All rights reserved
Keywords: math
Classifier: Programming Language :: Python :: 3
Classifier: License :: OSI Approved :: MIT License
Classifier: Operating System :: OS Independent
Classifier: Development Status :: 2 - Pre-Alpha
Requires-Python: >=3.6
License-File: LICENSE.md
Requires-Dist: numpy
Requires-Dist: colr
Requires-Dist: wasabi
Requires-Dist: typing_extensions; python_version < "3.7"
Provides-Extra: dev
Requires-Dist: mypy; extra == "dev"
Requires-Dist: pytest; extra == "dev"
Requires-Dist: pytest-cov; extra == "dev"
Requires-Dist: black; extra == "dev"
Requires-Dist: flake8; extra == "dev"
Requires-Dist: isort; extra == "dev"
Requires-Dist: autoflake; extra == "dev"
Requires-Dist: typer; extra == "dev"
Requires-Dist: mathy_pydoc; extra == "dev"
Provides-Extra: all
Requires-Dist: mypy; extra == "all"
Requires-Dist: pytest; extra == "all"
Requires-Dist: pytest-cov; extra == "all"
Requires-Dist: black; extra == "all"
Requires-Dist: flake8; extra == "all"
Requires-Dist: isort; extra == "all"
Requires-Dist: autoflake; extra == "all"
Requires-Dist: typer; extra == "all"
Requires-Dist: mathy_pydoc; extra == "all"
Dynamic: author
Dynamic: author-email
Dynamic: classifier
Dynamic: description
Dynamic: description-content-type
Dynamic: home-page
Dynamic: keywords
Dynamic: license
Dynamic: provides-extra
Dynamic: requires-dist
Dynamic: requires-python
Dynamic: summary
